<?xml version="1.0" encoding="utf-8" ?><dwsync><file name="Flat1.jpg" server="webdesign.digitalmediauconn.org" local="3513095544" remote="3513084720" Dst="-1" /><file name="Flat3.jpg" server="webdesign.digitalmediauconn.org" local="3513095566" remote="3513084720" Dst="-1" /><file name="Flat2.jpg" server="webdesign.digitalmediauconn.org" local="3513095575" remote="3513084720" Dst="-1" /><file name="JFosterLogo.png" server="webdesign.digitalmediauconn.org" local="3513099727" remote="3513088680" Dst="-1" /><file name="FacebookIcon.png" server="webdesign.digitalmediauconn.org" local="3513095607" remote="3513084720" Dst="-1" /><file name="TwitterIcon.png" server="webdesign.digitalmediauconn.org" local="3513095617" remote="3513084780" Dst="-1" /><file name="Pie300.jpg" server="webdesign.digitalmediauconn.org" local="3513095576" remote="3513084780" Dst="-1" /><file name="Pie500.jpg" server="webdesign.digitalmediauconn.org" local="3513095580" remote="3513084780" Dst="-1" /><file name="Pie750.jpg" server="webdesign.digitalmediauconn.org" local="3513095584" remote="3513084780" Dst="-1" /><file name="ReesesCake300.jpg" server="webdesign.digitalmediauconn.org" local="3513095580" remote="3513084780" Dst="-1" /><file name="ReesesCake1000.jpg" server="webdesign.digitalmediauconn.org" local="3513099237" remote="3513088200" Dst="-1" /><file name="ReesesCake500.jpg" server="webdesign.digitalmediauconn.org" local="3513095583" remote="3513084780" Dst="-1" /><file name="SunflowerCupcake300.jpg" server="webdesign.digitalmediauconn.org" local="3513095589" remote="3513084780" Dst="-1" /><file name="SunflowerCupcake500.jpg" server="webdesign.digitalmediauconn.org" local="3513095593" remote="3513084780" Dst="-1" /><file name="SunflowerCupcake750.jpg" server="webdesign.digitalmediauconn.org" local="3513095593" remote="3513084780" Dst="-1" /><file name="Cake300.jpg" server="webdesign.digitalmediauconn.org" local="3513095430" remote="3513084720" Dst="-1" /><file name="Cake600.jpg" server="webdesign.digitalmediauconn.org" local="3513095431" remote="3513084720" Dst="-1" /><file name="Cake750.jpg" server="webdesign.digitalmediauconn.org" local="3513095438" remote="3513084720" Dst="-1" /><file name="Cone300.jpg" server="webdesign.digitalmediauconn.org" local="3513095489" remote="3513084720" Dst="-1" /><file name="Cone500.jpg" server="webdesign.digitalmediauconn.org" local="3513095503" remote="3513084720" Dst="-1" /><file name="Cone750.jpg" server="webdesign.digitalmediauconn.org" local="3513123400" remote="3513150480" Dst="-1" /><file name="Fudge300.jpg" server="webdesign.digitalmediauconn.org" local="3513095527" remote="3513084720" Dst="-1" /><file name="Fudge500.jpg" server="webdesign.digitalmediauconn.org" local="3513095560" remote="3513084720" Dst="-1" /><file name="Fudge750.jpg" server="webdesign.digitalmediauconn.org" local="3513095581" remote="3513084720" Dst="-1" /><file name="KidsSupreme300.jpg" server="webdesign.digitalmediauconn.org" local="3513095568" remote="3513084720" Dst="-1" /><file name="KidsSupreme500.jpg" server="webdesign.digitalmediauconn.org" local="3513095573" remote="3513084720" Dst="-1" /><file name="OreoSandwich1200.jpg" server="webdesign.digitalmediauconn.org" local="3513123400" remote="3513150480" Dst="-1" /><file name="KidsSupreme750.jpg" server="webdesign.digitalmediauconn.org" local="3513095575" remote="3513084780" Dst="-1" /><file name="OreoSandwich300.jpg" server="webdesign.digitalmediauconn.org" local="3513095572" remote="3513084780" Dst="-1" /><file name="OreoSandwich600.jpg" server="webdesign.digitalmediauconn.org" local="3513095573" remote="3513084780" Dst="-1" /><file name="Cake1200.jpg" server="webdesign.digitalmediauconn.org" local="3513123400" remote="3513150480" Dst="-1" /><file name="CashewCaramel300.jpg" server="webdesign.digitalmediauconn.org" local="3513095431" remote="3513084720" Dst="-1" /><file name="CashewCaramel1200.jpg" server="webdesign.digitalmediauconn.org" local="3513123400" remote="3513150480" Dst="-1" /><file name="CashewCaramel600.jpg" server="webdesign.digitalmediauconn.org" local="3513095432" remote="3513084720" Dst="-1" /><file name="Sundae300.jpg" server="webdesign.digitalmediauconn.org" local="3513095587" remote="3513084780" Dst="-1" /><file name="Sundae500.jpg" server="webdesign.digitalmediauconn.org" local="3513095592" remote="3513084780" Dst="-1" /><file name="Sundae750.jpg" server="webdesign.digitalmediauconn.org" local="3513123400" remote="3513150480" Dst="-1" /><file name="IceCream300.jpg" server="webdesign.digitalmediauconn.org" local="3513095560" remote="3513084720" Dst="-1" /><file name="IceCream1200.jpg" server="webdesign.digitalmediauconn.org" local="3513095570" remote="3513084720" Dst="-1" /><file name="IceCream600.jpg" server="webdesign.digitalmediauconn.org" local="3513095562" remote="3513084720" Dst="-1" /><file name="Sorbet300.jpg" server="webdesign.digitalmediauconn.org" local="3513095584" remote="3513084780" Dst="-1" /><file name="Sorbet1200.jpg" server="webdesign.digitalmediauconn.org" local="3513095587" remote="3513084780" Dst="-1" /><file name="Sorbet600.jpg" server="webdesign.digitalmediauconn.org" local="3513095584" remote="3513084780" Dst="-1" /><file name="CherryCupcake300.jpg" server="webdesign.digitalmediauconn.org" local="3513095433" remote="3513084720" Dst="-1" /><file name="CherryCupcake500.jpg" server="webdesign.digitalmediauconn.org" local="3513095441" remote="3513084720" Dst="-1" /><file name="CherryCupcake750.jpg" server="webdesign.digitalmediauconn.org" local="3513095446" remote="3513084720" Dst="-1" /><file name="WaffleCone300.jpg" server="webdesign.digitalmediauconn.org" local="3513095593" remote="3513084780" Dst="-1" /><file name="WaffleCone500.jpg" server="webdesign.digitalmediauconn.org" local="3513095596" remote="3513084780" Dst="-1" /><file name="WaffleCone750.jpg" server="webdesign.digitalmediauconn.org" local="3513095596" remote="3513084780" Dst="-1" /><file name="IceCreamHead1200.jpg" server="webdesign.digitalmediauconn.org" local="3513095571" remote="3513084720" Dst="-1" /><file name=".DS_Store" server="webdesign.digitalmediauconn.org" local="3513161497" remote="3513150480" Dst="-1" /><file name="Grad Special 2015.jpg" server="webdesign.digitalmediauconn.org" local="3513107469" remote="3513150480" Dst="-1" /></dwsync>